timeflux_openbci/__init__.py
timeflux_openbci/nodes/__init__.py
timeflux_openbci/nodes/driver.py
timeflux_openbci-0.4.0.dist-info/LICENSE
timeflux_openbci-0.4.0.dist-info/METADATA
timeflux_openbci-0.4.0.dist-info/WHEEL
timeflux_openbci-0.4.0.dist-info/top_level.txt
timeflux_openbci-0.4.0.dist-info/RECORD
